README.rst
setup.cfg
setup.py
django_elasticfilter.egg-info/PKG-INFO
django_elasticfilter.egg-info/SOURCES.txt
django_elasticfilter.egg-info/dependency_links.txt
django_elasticfilter.egg-info/not-zip-safe
django_elasticfilter.egg-info/requires.txt
django_elasticfilter.egg-info/top_level.txt
elasticfilter/__init__.py
elasticfilter/fields.py
elasticfilter/filterform.py