Metadata-Version: 1.1
Name: django-elasticfilter
Version: 0.1.0
Summary: Create forms that run Elasticsearch queries
Home-page: https://bitbucket.org/tim_heap/django-elasticfilter/
Author: Tim Heap
Author-email: tim@timheap.me
License: BSD License
Platform: UNKNOWN
Classifier: Environment :: Web Environment
Classifier: Intended Audience :: Developers
Classifier: Operating System :: OS Independent
Classifier: Programming Language :: Python
Classifier: Framework :: Django
Classifier: License :: OSI Approved :: BSD License
